{"inkVersion":21,"root":[["^This is a loop","\n","\n","^Make your choices...","\n","ev","str","^Test Option","/str","/ev",{"*":"0.c-0","flg":4},["ev",{"^->":"0.11.$r1"},{"temp=":"$r"},"str",{"->":".^.s"},[{"#n":"$r1"}],"/str","/ev",{"*":"0.c-1","flg":2},{"s":["^Change scenes ",{"->":"$r","var":true},null]}],{"c-0":["^ it works","\n",{"->":"0.g-0"},{"#f":5}],"c-1":["ev",{"^->":"0.c-1.$r2"},"/ev",{"temp=":"$r"},{"->":"0.11.s"},[{"#n":"$r2"}],{"->":"TestKnot"},"\n","#","^~ changeScene(\"test\")","/#",{"->":"0.g-0"},{"#f":5}],"g-0":["^Stuff down here ","ev",{"VAR?":"test2"},"out","/ev","\n","ev",{"VAR?":"test2"},1,"+",{"VAR=":"test2","re":true},"/ev",["ev",{"^->":"0.g-0.12.$r1"},{"temp=":"$r"},"str",{"->":".^.s"},[{"#n":"$r1"}],"/str","/ev",{"*":".^.^.c-2","flg":2},{"s":["^Continue ","ev",{"VAR?":"test2"},"out","/ev",{"->":"$r","var":true},null]}],{"c-2":["ev",{"^->":"0.g-0.c-2.$r2"},"/ev",{"temp=":"$r"},{"->":".^.^.12.s"},[{"#n":"$r2"}],"\n","end",{"->":"0.g-1"},{"#f":5}],"#f":5}],"g-1":["done",{"#f":5}]}],"done",{"TestKnot":[["^I'm sorry your princess is in another castle.","\n","ev",{"VAR?":"test2"},1,"+",{"VAR=":"test2","re":true},"/ev",["ev",{"^->":"TestKnot.0.8.$r1"},{"temp=":"$r"},"str",{"->":".^.s"},[{"#n":"$r1"}],"/str","/ev",{"*":".^.^.c-0","flg":2},{"s":["^Continue ","ev",{"VAR?":"test2"},"out","/ev",{"->":"$r","var":true},null]}],{"c-0":["ev",{"^->":"TestKnot.0.c-0.$r2"},"/ev",{"temp=":"$r"},{"->":".^.^.8.s"},[{"#n":"$r2"}],"\n","done",{"#f":5}]}],{"#f":1}],"TestKnot2":[["^THIS IS YET ANOTHER KNOT ","ev",{"VAR?":"boolTest"},"out","/ev","\n","ev",{"VAR?":"boolTest"},"!","/ev",{"VAR=":"boolTest","re":true},["ev",{"^->":"TestKnot2.0.11.$r1"},{"temp=":"$r"},"str",{"->":".^.s"},[{"#n":"$r1"}],"/str","/ev",{"*":".^.^.c-0","flg":2},{"s":["^Continue",{"->":"$r","var":true},null]}],{"c-0":["ev",{"^->":"TestKnot2.0.c-0.$r2"},"/ev",{"temp=":"$r"},{"->":".^.^.11.s"},[{"#n":"$r2"}],"\n","done",{"#f":5}]}],{"#f":1}],"TestKnot3":[["^List Knot ","ev",{"VAR?":"currentColor"},"out","/ev","\n","ev",{"VAR?":"currentColor"},1,"+",{"VAR=":"currentColor","re":true},"/ev",["ev",{"^->":"TestKnot3.0.12.$r1"},{"temp=":"$r"},"str",{"->":".^.s"},[{"#n":"$r1"}],"/str","/ev",{"*":".^.^.c-0","flg":2},{"s":["^Continue",{"->":"$r","var":true},null]}],{"c-0":["ev",{"^->":"TestKnot3.0.c-0.$r2"},"/ev",{"temp=":"$r"},{"->":".^.^.12.s"},[{"#n":"$r2"}],"\n","done",{"#f":5}]}],{"#f":1}],"TestKnot4":[["^THIS IS TEST 4 KNOT","ev",{"VAR?":"boolTest"},"out","/ev","\n","ev",{"VAR?":"boolTest"},"!","/ev",{"VAR=":"boolTest","re":true},["ev",{"^->":"TestKnot4.0.11.$r1"},{"temp=":"$r"},"str",{"->":".^.s"},[{"#n":"$r1"}],"/str","/ev",{"*":".^.^.c-0","flg":2},{"s":["^Continue",{"->":"$r","var":true},null]}],{"c-0":["ev",{"^->":"TestKnot4.0.c-0.$r2"},"/ev",{"temp=":"$r"},{"->":".^.^.11.s"},[{"#n":"$r2"}],"\n","done",{"#f":5}]}],{"#f":1}],"TestKnot5":[["^Make your choices...","\n","ev","str","^Test Option","/str","/ev",{"*":".^.c-0","flg":4},["ev",{"^->":"TestKnot5.0.8.$r1"},{"temp=":"$r"},"str",{"->":".^.s"},[{"#n":"$r1"}],"/str","/ev",{"*":".^.^.c-1","flg":2},{"s":["^Change scenes ",{"->":"$r","var":true},null]}],{"c-0":["^ it works","\n",{"->":".^.^.g-0"},{"#f":5}],"c-1":["ev",{"^->":"TestKnot5.0.c-1.$r2"},"/ev",{"temp=":"$r"},{"->":".^.^.8.s"},[{"#n":"$r2"}],{"->":"TestKnot"},"\n","#","^~ changeScene(\"test\")","/#",{"->":".^.^.g-0"},{"#f":5}],"g-0":["^Stuff down here ","ev",{"VAR?":"test2"},"out","/ev","\n","ev",{"VAR?":"test2"},1,"+",{"VAR=":"test2","re":true},"/ev",["ev",{"^->":"TestKnot5.0.g-0.12.$r1"},{"temp=":"$r"},"str",{"->":".^.s"},[{"#n":"$r1"}],"/str","/ev",{"*":".^.^.c-2","flg":2},{"s":["^Continue ","ev",{"VAR?":"test2"},"out","/ev",{"->":"$r","var":true},null]}],{"c-2":["ev",{"^->":"TestKnot5.0.g-0.c-2.$r2"},"/ev",{"temp=":"$r"},{"->":".^.^.12.s"},[{"#n":"$r2"}],"\n","end",{"#f":5}],"#f":5}]}],{"#f":1}],"TestPresent":[["^Time to present","\n","ev","str","^::Continue","/str","/ev",{"*":".^.c-0","flg":4},{"c-0":["\n","ev","str","^PresentSubmit","/str",{"x()":"presentEvidence","exArgs":1},"pop","/ev","\n","done",{"#f":5}]}],{"#f":1}],"PresentSubmit":["^TEST ","ev",{"VAR?":"submittedEvidence"},"out","/ev","\n","ev",{"VAR?":"submittedEvidence"},"str","^testCorrect","/str","==","/ev",[{"->":".^.b","c":true},{"b":["\n","ev","str","^","/str",{"x()":"correctEvidence","exArgs":1},"pop","/ev","\n",{"->":"CorrectSubmission"},{"->":".^.^.^.15"},null]}],[{"->":".^.b"},{"b":["\n",{"->":"WrongSubmission"},{"->":".^.^.^.15"},null]}],"nop","\n","done",{"#f":1}],"WrongSubmission":[["^That is wrong!","\n","ev","str","^::Continue","/str","/ev",{"*":".^.c-0","flg":4},{"c-0":["\n","done",{"#f":5}]}],{"#f":1}],"CorrectSubmission":[["^You did it!","\n","ev","str","^::Continue","/str","/ev",{"*":".^.c-0","flg":4},{"c-0":["\n","done",{"#f":5}]}],{"#f":1}],"global decl":["ev",6,{"VAR=":"test2"},false,{"VAR=":"boolTest"},{"list":{},"origins":["listTest"]},{"VAR=":"listTest"},{"VAR?":"red"},{"VAR=":"currentColor"},"str","^","/str",{"VAR=":"submittedEvidence"},"/ev","end",null],"#f":1}],"listDefs":{"listTest":{"red":1,"orange":2,"yellow":3,"green":4,"blue":5}}}